attributetools.py
attributetools-0.1.1.dist-info/DESCRIPTION.rst
attributetools-0.1.1.dist-info/metadata.json
attributetools-0.1.1.dist-info/RECORD
attributetools-0.1.1.dist-info/WHEEL
attributetools-0.1.1.dist-info/top_level.txt
attributetools-0.1.1.dist-info/METADATA
