Metadata-Version: 2.0
Name: attributetools
Version: 0.1.1
Summary: A decorator to set some attribute to a function.
Home-page: https://github.com/paulo-romano/attributetools
Author: Paulo Romano
Author-email: pauloromanocarvalho@gmail.com
License: MIT
Download-URL: https://github.com/paulo-romano/attributetools/tarball/0.1
Platform: any
Classifier: Development Status :: 3 - Alpha
Classifier: Framework :: Django
Classifier: Intended Audience :: Developers
Classifier: License :: OSI Approved :: MIT License
Classifier: Natural Language :: English
Classifier: Operating System :: OS Independent
Classifier: Programming Language :: Python
Classifier: Programming Language :: Python :: 3
Classifier: Topic :: Software Development :: Libraries
